aiocacher/__init__.py
aiocacher/backends/__init__.py
aiocacher/backends/_base.py
aiocacher/backends/redis.py
aiocacher/cache.py
aiocacher/plugins/__init__.py
aiocacher/plugins/_base.py
aiocacher/plugins/stats.py
aiocacher/py.typed
aiocacher/serializers/__init__.py
aiocacher/serializers/_base.py
aiocacher/serializers/serializers.py
aiocacher/types.py
aiocacher/utils.py
aiocacher-0.1.6.dist-info/LICENSE
aiocacher-0.1.6.dist-info/WHEEL
aiocacher-0.1.6.dist-info/METADATA
aiocacher-0.1.6.dist-info/RECORD
