Metadata-Version: 2.1
Name: aiocacher
Version: 0.1.6
Summary: Python asyncio caching decorator backed by a Redis server or cluster.
License: MIT
Author: Blake VandeMerwe
Author-email: blakev@null.net
Requires-Python: >=3.8,<4.0
Classifier: License :: OSI Approved :: MIT License
Classifier: Programming Language :: Python :: 3
Classifier: Programming Language :: Python :: 3.8
Classifier: Programming Language :: Python :: 3.9
Provides-Extra: dill
Provides-Extra: ujson
Requires-Dist: aioredis (>=2.0.0)
Requires-Dist: dill (>=0.3.4); extra == "dill"
Requires-Dist: hiredis (>=2.0.0)
Requires-Dist: toolz (>=0.11.0)
Requires-Dist: ujson (>=5.1.0); extra == "ujson"
